Workbook

Sheet DASHBOARD
A1: ⚡ TRADING BOOK — DASHBOARD
A3: Портфель
A4: Эквити (USDT) | B4: =IFERROR(DAILY!B2,"")
A5: IM использовано | B5: =IFERROR(DAILY!C2,"")
A6: MM | B6: =IFERROR(DAILY!D2,"")
A7: P&L сегодня | B7: =IFERROR(DAILY!E2,"")
A9: P&L по конструктам (день)
A10: C1 Locked Spread | B10: =IFERROR(DAILY!F2,"")
A11: C2 Stat-Arb Pair | B11: =IFERROR(DAILY!G2,"")
A12: C3 Synth Ratio | B12: =IFERROR(DAILY!H2,"")
A13: C4 Opt Calendar | B13: =IFERROR(DAILY!I2,"")
A15: Риск-индикаторы
A16: Z-score C2 (XAU) | B16: =IFERROR(DAILY!L2,"")
A17: Ratio Z-score C3 | B17: =IFERROR(DAILY!N2,"")
A18: Basis C1 (спот-перп) | B18: =IFERROR(DAILY!K2,"")
A19: Margin ratio | B19: =IFERROR(DAILY!C2/DAILY!B2,"")

Sheet CONSTRUCTS
A1: id | B1: type | C1: name | D1: status | E1: open_date | F1: close_date | G1: notional_usd | H1: realized_pnl | I1: unrealized_pnl | J1: net_delta_usd | K1: net_gamma | L1: net_theta | M1: net_vega | N1: notes
A2: C1 | B2: LOCKED_SPREAD | C2: XAUTUSDT Spot/Perp | D2: active | E2: 46183 | G2: 0 | H2: 0 | I2: 0 | J2: 0 | K2: 0 | L2: 0 | M2: 0 | N2: лонг спот + шорт перп XAUTUSDT
A3: C2 | B3: STATARB_PAIR | C3: XAUUSDT Rev + XAGUSDT Trend | D3: active | E3: 46183 | G3: 0 | H3: 0 | I3: 0 | J3: 0 | K3: 0 | L3: 0 | M3: 0 | N3: реверсия XAU / тренд XAG h*≈0.41
A4: C3 | B4: SYNTH_RATIO | C4: XAUT/XAG Ratio + Options | D4: active | E4: 46183 | G4: 0 | H4: 0 | I4: 0 | J4: 0 | K4: 0 | L4: 0 | M4: 0 | N4: ratio convergence + optn wrapper
A5: C4 | B5: OPT_CALENDAR | C5: XAUTUSDT Opt Calendar ATM | D5: active | E5: 46183 | G5: 0 | H5: 0 | I5: 0 | J5: 0 | K5: 0 | L5: 0 | M5: 0 | N5: near/far synth future ATM

Sheet LEGS
A1: construct_id | B1: leg_id | C1: leg_role | D1: instrument | E1: category | F1: direction | G1: qty | H1: entry_price | I1: current_price | J1: notional_usd | K1: unrealized_pnl | L1: delta | M1: gamma | N1: theta | O1: vega | P1: status | Q1: notes
A2: C1 | B2: C1_L1 | C2: spot_long | D2: XAUTUSDT | E2: spot | F2: long | G2: 0 | H2: 0 | I2: 0 | J2: =G2*H2 | K2: =(I2-H2)*G2 | L2: 1 | M2: 0 | N2: 0 | O2: 0 | P2: open | Q2: спот-сетка лонг
A3: C1 | B3: C1_L2 | C3: perp_short | D3: XAUTUSDT | E3: perp | F3: short | G3: 0 | H3: 0 | I3: 0 | J3: =G3*H3 | K3: =(H3-I3)*G3 | L3: -1 | M3: 0 | N3: 0 | O3: 0 | P3: open | Q3: перп-сетка шорт
A4: C2 | B4: C2_L1 | C4: reversion_perp | D4: XAUUSDT | E4: perp | F4: long | G4: 0 | H4: 0 | I4: 0 | J4: =G4*H4 | K4: =(I4-H4)*G4 | L4: 1 | M4: 0 | N4: 0 | O4: 0 | P4: open | Q4: реверсионная
A5: C2 | B5: C2_L2 | C5: trend_perp | D5: XAGUSDT | E5: perp | F5: long | G5: 0 | H5: 0 | I5: 0 | J5: =G5*H5 | K5: =(I5-H5)*G5 | L5: 1 | M5: 0 | N5: 0 | O5: 0 | P5: open | Q5: трендовая XAG
A6: C3 | B6: C3_L1 | C6: ratio_long | D6: XAUTUSDT | E6: perp | F6: long | G6: 0 | H6: 0 | I6: 0 | J6: =G6*H6 | K6: =(I6-H6)*G6 | L6: 1 | M6: 0 | N6: 0 | O6: 0 | P6: open | Q6: ratio long leg
A7: C3 | B7: C3_L2 | C7: ratio_short | D7: XAGUSDT | E7: perp | F7: short | G7: 0 | H7: 0 | I7: 0 | J7: =G7*H7 | K7: =(H7-I7)*G7 | L7: -1 | M7: 0 | N7: 0 | O7: 0 | P7: open | Q7: ratio short leg h*
A8: C3 | B8: C3_L3 | C8: otm_bought | D8: XAUT-?-?-C | E8: option | F8: long | G8: 0 | H8: 0 | I8: 0 | J8: =G8*H8 | K8: =(I8-H8)*G8 | L8: 0 | M8: 0 | N8: 0 | O8: 0 | P8: open | Q8: купленный OTM колл
A9: C3 | B9: C3_L4 | C9: otm_sold | D9: XAUT-?-?-P | E9: option | F9: short | G9: 0 | H9: 0 | I9: 0 | J9: =G9*H9 | K9: =(H9-I9)*G9 | L9: 0 | M9: 0 | N9: 0 | O9: 0 | P9: open | Q9: проданный OTM пут
A10: C4 | B10: C4_L1 | C10: synth_near | D10: XAUT-near-ATM | E10: synth_future | F10: long | G10: 0 | H10: 0 | I10: 0 | J10: =G10*H10 | K10: =(I10-H10)*G10 | L10: 1 | M10: 0 | N10: 0 | O10: 0 | P10: open | Q10: near synth: long C + short P
A11: C4 | B11: C4_L2 | C11: synth_far | D11: XAUT-far-ATM | E11: synth_future | F11: short | G11: 0 | H11: 0 | I11: 0 | J11: =G11*H11 | K11: =(H11-I11)*G11 | L11: -1 | M11: 0 | N11: 0 | O11: 0 | P11: open | Q11: far synth: short C + long P

Sheet GRID_FILLS
A1: date | B1: construct_id | C1: leg_id | D1: instrument | E1: fill_type | F1: direction | G1: qty | H1: price | I1: value_usd | J1: fee_usd | K1: pnl_usd | L1: grid_level | M1: notes
A2: 46183 | B2: C1 | C2: C1_L1 | D2: XAUTUSDT | E2: limit_buy | F2: buy | G2: 0.01 | H2: 4245 | I2: =G2*H2 | J2: 0.12 | K2: 0 | L2: 1 | M2: пример — заменить на реальные данные

Sheet OPT_EVENTS
A1: date | B1: construct_id | C1: leg_id | D1: event_type | E1: symbol | F1: option_type | G1: strike | H1: expiry | I1: direction | J1: qty | K1: premium_usd | L1: total_usd | M1: fee_usd | N1: delta | O1: gamma | P1: theta | Q1: vega | R1: iv_pct | S1: pnl_usd | T1: notes

Sheet DAILY
A1: date | B1: equity_usd | C1: im_usd | D1: mm_usd | E1: pnl_day | F1: pnl_C1 | G1: pnl_C2 | H1: pnl_C3 | I1: pnl_C4 | J1: funding_day | K1: theta_day | L1: basis_C1 | M1: z_score_C2 | N1: ratio_C3 | O1: ratio_z_C3 | P1: notes

Sheet PARAMS
A1: [C1] Locked Spread — XAUTUSDT Spot/Perp
A2: spot_lower | B2: 4000 | C2: Нижняя граница спот-сетки $
A3: spot_upper | B3: 4500 | C3: Верхняя граница спот-сетки $
A4: spot_steps | B4: 20 | C4: Уровней спот-сетки
A5: spot_qty_per_step | B5: 0.01 | C5: XAUT на уровень
A6: perp_lower | B6: 4000 | C6: Нижняя граница перп-сетки $
A7: perp_upper | B7: 4500 | C7: Верхняя граница перп-сетки $
A8: perp_steps | B8: 20 | C8: Уровней перп-сетки
A9: perp_qty_per_step | B9: 0.01 | C9: Контрактов на уровень
A10: leverage_perp | B10: 5 | C10: Плечо перп-ноги
A12: [C2] Stat-Arb Pair — XAUUSDT Rev + XAG Trend
A13: xau_mu | B13: 0 | C13: Среднее XAUUSDT (последние N баров)
A14: xau_sigma | B14: 0 | C14: σ XAUUSDT
A15: half_life_bars | B15: 38 | C15: AR(1) полужизнь (бары)
A16: k_entry | B16: 2 | C16: Z-порог входа
A17: k_exit | B17: 0.5 | C17: Z-порог выхода
A18: xau_qty | B18: 0 | C18: Размер позиции XAU (контракты)
A19: h_star | B19: 0.41 | C19: Хедж-коэф к XAG
A20: xag_lower | B20: 60 | C20: Нижняя граница XAG-сетки $
A21: xag_upper | B21: 75 | C21: Верхняя граница XAG-сетки $
A23: [C3] Synth Ratio — XAUT/XAG + Options
A24: entry_ratio | B24: 0 | C24: XAUT/XAG при входе
A25: target_ratio | B25: 0 | C25: Цель — μ ratio
A26: ratio_mu | B26: 0 | C26: Скользящее среднее ratio
A27: ratio_sigma | B27: 0 | C27: σ ratio
A28: h_star | B28: 0.41 | C28: Хедж-коэф h*
A29: xaut_notional | B29: 0 | C29: Ноционал XAUT $
A30: xag_notional | B30: 0 | C30: Ноционал XAG $ (= xaut × h*)
A31: otm_call_strikes | B31: [] | C31: Страйки купленных коллов
A32: otm_put_strikes | B32: [] | C32: Страйки купленных путов
A33: sold_call_strikes | B33: [] | C33: Страйки проданных коллов
A34: sold_put_strikes | B34: [] | C34: Страйки проданных путов
A36: [C4] Opt Calendar — XAUTUSDT ATM
A37: near_expiry | B37: 2026-06-12 | C37: Ближняя экспирация
A38: far_expiry | B38: 2026-07-31 | C38: Дальняя экспирация
A39: strike_atm | B39: 4250 | C39: ATM страйк (≈ near forward)
A40: entry_spread | B40: 0 | C40: Спред at entry (near-far)
A41: target_spread | B41: 0 | C41: Цель при схождении к споту
A42: qty | B42: 1 | C42: Лотов

Sheet FORMULAS_REF
A1: ФОРМУЛА | B1: ВЫРАЖЕНИЕ | C1: ПРИМЕЧАНИЕ
A2: h* (хедж-коэф) | B2: ρ × σ_XAU / σ_XAG | C2: min-variance hedge ratio
A3: Z-score | B3: (value − μ) / σ | C3: сигнал входа при |Z| > k
A4: Basis | B4: futures_price − spot_price | C4: + = contango, − = backwardation
A5: Synth future | B5: long call(K) + short put(K) | C5: страйк K = ATM forward
A6: Calendar spread | B6: near_synth_price − far_synth_price | C6: собираем при contango
A7: $-delta | B7: Σ (delta_i × price_i) | C7: НЕ сумма дельт в штуках!
A8: Net gamma $ | B8: Σ (gamma_i × price_i²) | C8: нормировано по ноционалу
A9: APR сетки | B9: (realized_pnl / investment) / days × 365 × 100 | C9: % годовых фактических
A10: Locked basis P&L | B10: (perp_entry − spot_entry) − (perp_exit − spot_exit) | C10: схождение спреда
A11: Ratio entry signal | B11: Z_ratio > +2 → шорт XAUT / лонг XAG | C11: ratio уйдёт к μ
A12: Half-life (AR1) | B12: −ln(2) / ln(β) | C12: β = коэф. AR(1) регрессии
A13: IV/RV threshold | B13: IV / RV > 1.2 → продаём волу | C13: 20% premium к реализованной
