Workbook

Sheet Калькулятор
A1: СТАТ-АРБ — КАЛЬКУЛЯТОР (кросс-венью спред)
A2: Жёлтое = ввод (синий шрифт). Чёрное = формула. Зеркалит вкладку «Стат-арб 🔱».
A3: ПАРАМЕТР | C3: Нога A | D3: Нога B
A4: Метка / тикер | C4: XAUTUSDT.bybit | D4: XAUEUR.infra
A5: Площадка | C5: Bybit | D5: Infra Capital
A6: Цена | C6: 4021.2 | D6: 3724
A7: FX → USD | C7: 1 | D7: 1.08
A8: $ / пункт | C8: 1 | D8: 1
A9: Вола % | C9: 15 | D9: 15
A10: TV-символ | C10: OANDA:XAUUSD | D10: OANDA:XAUEUR*FX_IDC:EURUSD
A11: Цена в USD | C11: =C6*C7 -> 4021.2 | D11: =D6*D7 -> 4021.92
A12: Ноционал / ед, $ | C12: =C11*C8 -> 4021.2 | D12: =D11*D8 -> 4021.92
A14: ПАРАМЕТРЫ
A15: Метод ратио | C15: notional
A16: β ручной (ед B на ед A) | C16: 1
A17: Капитал / сторона, $ | C17: 1000
A18: Хедж-ратио h (ед B на 1 A) | C18: =IF(C15="notional",C12/D12,IF(C15="vol",(C12*C9)/(D12*D9),C16)) -> 0.99982098
A19: Units A | C19: =C17/C12 -> 0.24868199
A20: Units B | C20: =C19*C18 -> 0.24863747
A21: Ноционал A, $ | C21: =C19*C12 -> 1000
A22: Ноционал B, $ | C22: =C20*D12 -> 1000
A24: СИГНАЛ
A25: Режим (diff/ratio/pct) | C25: diff
A26: Спред авто | C26: =IF(C25="ratio",C11/D11,IF(C25="pct",(C11/D11-1)*100,C11-C18*D11)) -> 0
A27: Спред сейчас (пусто=авто)
A28: Спред используемый | C28: =IF(C27="",C26,C27) -> 0
A29: μ среднее | C29: 0
A30: σ спреда | C30: 5
A31: Порог Z | C31: 2
A32: Z-score | C32: =IF(C30=0,0,(C28-C29)/C30) -> 0
A33: СИГНАЛ | C33: =IF(C32>=C31,"ШОРТ A / ЛОНГ B (спред дорог)",IF(C32<=-C31,"ЛОНГ A / ШОРТ B (спред дёшев)","ждать (внутри полосы)")) -> ждать (внутри полосы)
A34: P&L цель к μ, $ | C34: =IF(C25="diff",ABS(C28-C29)*C19*C8,"оцени по графику") -> 0
A36: TV-ФОРМУЛА
A37: Формула спреда | C37: =IF(C25="ratio",C10&"/("&D10&")",IF(C25="pct","("&C10&"/("&D10&")-1)*100",C10&" - "&TEXT(C18,"0.0000")&"*("&D10&")")) -> OANDA:XAUUSD - 0.9998*(OANDA:XAUEUR*FX_IDC:EURUSD)
A38: → вставь как символ в TradingView; снимай μ/σ с этого графика

Sheet Журнал
A1: Дата | B1: Пара | C1: Класс актива | D1: Нога A | E1: Площ. A | F1: Нога B | G1: Площ. B | H1: Метод | I1: Направление | J1: Хедж-ратио | K1: Спред вход | L1: μ | M1: σ | N1: Z вход | O1: Units A | P1: Units B | Q1: Ноционал/стор $ | R1: Время вход | S1: Спред выход | T1: Время выход | U1: Реализ.P&L $ | V1: Фи Bybit $ | W1: Своп/фи CFD $ | X1: Нетто P&L $ | Y1: Статус | Z1: Заметки
A2: 2026-06-30 | B2: XAUT/XAUEUR | C2: Золото | D2: XAUTUSDT.bybit | E2: Bybit | F2: XAUEUR.infra | G2: Infra | H2: notional | I2: ШОРТ A / ЛОНГ B | J2: 1 | K2: 15 | L2: 0 | M2: 5 | N2: =IF(OR(K2="",M2="",M2=0),"",(K2-L2)/M2) -> 3 | O2: 0.2487 | P2: 0.2486 | Q2: 1000 | R2: 08:20 | V2: 0.2 | W2: 1.5 | X2: =IF(U2="","",U2-IF(V2="",0,V2)-IF(W2="",0,W2)) | Y2: =IF(A2="","",IF(S2="","открыт","закрыт")) -> открыт | Z2: тест-сетап
N3: =IF(OR(K3="",M3="",M3=0),"",(K3-L3)/M3) | X3: =IF(U3="","",U3-IF(V3="",0,V3)-IF(W3="",0,W3)) | Y3: =IF(A3="","",IF(S3="","открыт","закрыт"))
N4: =IF(OR(K4="",M4="",M4=0),"",(K4-L4)/M4) | X4: =IF(U4="","",U4-IF(V4="",0,V4)-IF(W4="",0,W4)) | Y4: =IF(A4="","",IF(S4="","открыт","закрыт"))
N5: =IF(OR(K5="",M5="",M5=0),"",(K5-L5)/M5) | X5: =IF(U5="","",U5-IF(V5="",0,V5)-IF(W5="",0,W5)) | Y5: =IF(A5="","",IF(S5="","открыт","закрыт"))
N6: =IF(OR(K6="",M6="",M6=0),"",(K6-L6)/M6) | X6: =IF(U6="","",U6-IF(V6="",0,V6)-IF(W6="",0,W6)) | Y6: =IF(A6="","",IF(S6="","открыт","закрыт"))
N7: =IF(OR(K7="",M7="",M7=0),"",(K7-L7)/M7) | X7: =IF(U7="","",U7-IF(V7="",0,V7)-IF(W7="",0,W7)) | Y7: =IF(A7="","",IF(S7="","открыт","закрыт"))
N8: =IF(OR(K8="",M8="",M8=0),"",(K8-L8)/M8) | X8: =IF(U8="","",U8-IF(V8="",0,V8)-IF(W8="",0,W8)) | Y8: =IF(A8="","",IF(S8="","открыт","закрыт"))
N9: =IF(OR(K9="",M9="",M9=0),"",(K9-L9)/M9) | X9: =IF(U9="","",U9-IF(V9="",0,V9)-IF(W9="",0,W9)) | Y9: =IF(A9="","",IF(S9="","открыт","закрыт"))
N10: =IF(OR(K10="",M10="",M10=0),"",(K10-L10)/M10) | X10: =IF(U10="","",U10-IF(V10="",0,V10)-IF(W10="",0,W10)) | Y10: =IF(A10="","",IF(S10="","открыт","закрыт"))
N11: =IF(OR(K11="",M11="",M11=0),"",(K11-L11)/M11) | X11: =IF(U11="","",U11-IF(V11="",0,V11)-IF(W11="",0,W11)) | Y11: =IF(A11="","",IF(S11="","открыт","закрыт"))
N12: =IF(OR(K12="",M12="",M12=0),"",(K12-L12)/M12) | X12: =IF(U12="","",U12-IF(V12="",0,V12)-IF(W12="",0,W12)) | Y12: =IF(A12="","",IF(S12="","открыт","закрыт"))
N13: =IF(OR(K13="",M13="",M13=0),"",(K13-L13)/M13) | X13: =IF(U13="","",U13-IF(V13="",0,V13)-IF(W13="",0,W13)) | Y13: =IF(A13="","",IF(S13="","открыт","закрыт"))
N14: =IF(OR(K14="",M14="",M14=0),"",(K14-L14)/M14) | X14: =IF(U14="","",U14-IF(V14="",0,V14)-IF(W14="",0,W14)) | Y14: =IF(A14="","",IF(S14="","открыт","закрыт"))
... N61: =IF(OR(K61="",M61="",M61=0),"",(K61-L61)/M61) | X61: =IF(U61="","",U61-IF(V61="",0,V61)-IF(W61="",0,W61)) | Y61: =IF(A61="","",IF(S61="","открыт","закрыт"))

Sheet Сводка
A1: СВОДКА
A3: Всего сетапов | B3: =COUNTA(Журнал!A2:A61) -> 1
A4: Открыто | B4: =COUNTIF(Журнал!Y2:Y61,"открыт") -> 1
A5: Закрыто | B5: =COUNTIF(Журнал!Y2:Y61,"закрыт") -> 0
A6: Выигрышных | B6: =COUNTIFS(Журнал!Y2:Y61,"закрыт",Журнал!X2:X61,">0") -> 0
A7: Win rate | B7: =IF(B5=0,0,B6/B5) -> 0
A8: Нетто P&L, $ | B8: =SUM(Журнал!X2:X61) -> 0
A9: Валовой P&L, $ | B9: =SUM(Журнал!U2:U61) -> 0
A10: Сумма фи (Bybit+CFD), $ | B10: =SUM(Журнал!V2:V61)+SUM(Журнал!W2:W61) -> 1.7
A11: Средний Z входа (закрытых) | B11: =IFERROR(AVERAGEIFS(Журнал!N2:N61,Журнал!Y2:Y61,"закрыт"),0) -> 0
A12: Лучший сетап, $ | B12: =IFERROR(MAX(Журнал!X2:X61),0) -> 0
A13: Худший сетап, $ | B13: =IFERROR(MIN(Журнал!X2:X61),0) -> 0
A15: P&L по классу актива (заполни классы в Журнале, столбец C):
A16: Золото | B16: =SUMIF(Журнал!C2:C61,A16,Журнал!X2:X61) -> 0
A17: Серебро | B17: =SUMIF(Журнал!C2:C61,A17,Журнал!X2:X61) -> 0
A18: Платина | B18: =SUMIF(Журнал!C2:C61,A18,Журнал!X2:X61) -> 0
A19: BTC | B19: =SUMIF(Журнал!C2:C61,A19,Журнал!X2:X61) -> 0
A20: ETH | B20: =SUMIF(Журнал!C2:C61,A20,Журнал!X2:X61) -> 0
A21: Валюта | B21: =SUMIF(Журнал!C2:C61,A21,Журнал!X2:X61) -> 0

Sheet Задачи
A1: ЗАДАЧИ — триангулярный стат-арб (детсад → практик)
A2: Вписывай жёлтый «Твой ответ» → ✓ загорится само (допуск ±1%). Правильный ответ скрыт в столбце G — разверни, только если застрял.
A3: № | B3: Уровень | C3: Вопрос | D3: Твой ответ | E3: ✓ | F3: Подсказка / формула | G3: Ответ
A4: 1 | B4: 🧸 Детсад | C4: 1 EUR = 1.08 USD. Сколько USD за 50 EUR? | D4: 54 | E4: =IF(D4="","",IF(ABS(D4-G4)<=ABS(G4)*0.01+0.0001,"✓","✗")) -> ✓ | F4: умножь курс на количество | G4: =1.08*50 -> 54
A5: 2 | B5: 🧸 Детсад | C5: 1 USD = 150 JPY. Сколько JPY за 100 USD? | D5: 15000 | E5: =IF(D5="","",IF(ABS(D5-G5)<=ABS(G5)*0.01+0.0001,"✓","✗")) -> ✓ | F5: умножь | G5: =150*100 -> 15000
A6: 3 | B6: 🧸 Детсад | C6: 1 EUR = 1.08 USD и 1 USD = 150 JPY. Сколько JPY за 1 EUR через доллар? | E6: =IF(D6="","",IF(ABS(D6-G6)<=ABS(G6)*0.01+0.0001,"✓","✗")) | F6: перемножь два курса = синтетический EURJPY | G6: =1.08*150 -> 162
A7: 4 | B7: 🧸 Детсад | C7: У тебя 16 200 JPY, курс EURJPY = 162. Сколько это EUR? | E7: =IF(D7="","",IF(ABS(D7-G7)<=ABS(G7)*0.01+0.0001,"✓","✗")) | F7: дели сумму на курс | G7: =16200/162 -> 100
A8: 5 | B8: 🧸 Детсад | C8: Старт 100 EUR → доллары (×1.08) → йены (×150) → назад в EUR по EURJPY=162.30. Сколько EUR в конце? (<100 = потерял) | E8: =IF(D8="","",IF(ABS(D8-G8)<=ABS(G8)*0.01+0.0001,"✓","✗")) | F8: умножай при продаже, дели при выкупе | G8: =100*1.08*150/162.3 -> 99.815157
A9: 6 | B9: 🎒 Школа | C9: Синтетика EURJPY = 1.08×150. Прямая котировка = 162.30. Гэп в пунктах (йенах)? | E9: =IF(D9="","",IF(ABS(D9-G9)<=ABS(G9)*0.01+0.0001,"✓","✗")) | F9: прямая − синтетика | G9: =162.3-1.08*150 -> 0.3
A10: 7 | B10: 🎒 Школа | C10: Тот же гэп в процентах от синтетики? | E10: =IF(D10="","",IF(ABS(D10-G10)<=ABS(G10)*0.01+0.0001,"✓","✗")) | F10: (прямая/синт − 1)×100 | G10: =(162.3/(1.08*150)-1)*100 -> 0.18518519
A11: 8 | B11: 🎒 Школа | C11: EURJPY с 2 знаками, 1 пункт = 0.01. Гэп 0.30 = сколько пунктов? | E11: =IF(D11="","",IF(ABS(D11-G11)<=ABS(G11)*0.01+0.0001,"✓","✗")) | F11: дели гэп на размер пункта | G11: =0.3/0.01 -> 30
A12: 9 | B12: 🎒 Школа | C12: Круг проходит 3 ноги, каждая 0.04% туда-обратно. Сколько % съест весь круг? | E12: =IF(D12="","",IF(ABS(D12-G12)<=ABS(G12)*0.01+0.0001,"✓","✗")) | F12: сложи издержки трёх ног | G12: =3*0.04 -> 0.12
A13: 10 | B13: 🎒 Школа | C13: Край круга 0.185% против издержек 0.12%. Сколько нетто остаётся, %? | E13: =IF(D13="","",IF(ABS(D13-G13)<=ABS(G13)*0.01+0.0001,"✓","✗")) | F13: край − издержки; >0 = живой | G13: =0.185-0.12 -> 0.065
A14: 11 | B14: 🎒 Школа | C14: Лог-остаток x = ln(162.30) − ln(1.08) − ln(150). Посчитай. | E14: =IF(D14="","",IF(ABS(D14-G14)<=ABS(G14)*0.01+0.0001,"✓","✗")) | F14: натуральный лог, знаки (+,−,−) | G14: =LN(162.3)-LN(1.08)-LN(150) -> 0.0018501393
A15: 12 | B15: 🎓 Универ | C15: Коинтегрирующий вектор на (ln EURJPY, ln EURUSD, ln USDJPY)? Три числа. | E15: устно | F15: из тождества c=e·j → ln c − ln e − ln j = 0 | G15: (1; -1; -1)
A16: 13 | B16: 🎓 Универ | C16: Лонг 100 000 EUR ноционала в EURJPY. Какой USD-ноционал в EURUSD-ноге обнуляет EUR? (×1.08) | E16: =IF(D16="","",IF(ABS(D16-G16)<=ABS(G16)*0.01+0.0001,"✓","✗")) | F16: EUR-ноционал × курс EURUSD | G16: =100000*1.08 -> 108000
A17: 14 | B17: 🎓 Универ | C17: Та же корзина: JPY-ноционал в USDJPY-ноге? (EUR × 1.08 × 150) | E17: =IF(D17="","",IF(ABS(D17-G17)<=ABS(G17)*0.01+0.0001,"✓","✗")) | F17: прогон по цепочке валют 1 : e : e·j | G17: =100000*1.08*150 -> 16200000
A18: 15 | B18: 🎓 Универ | C18: Остаток: μ=0, σ=0.0003 (лог), текущий x=0.0008. z-score? | E18: =IF(D18="","",IF(ABS(D18-G18)<=ABS(G18)*0.01+0.0001,"✓","✗")) | F18: (x − μ) / σ | G18: =(0.0008-0)/0.0003 -> 2.6666667
A19: 16 | B19: 🎓 Универ | C19: Порог входа z=2, текущий z=2.667 — сигнал есть? (1=да, 0=нет) | E19: =IF(D19="","",IF(ABS(D19-G19)<=ABS(G19)*0.01+0.0001,"✓","✗")) | F19: сравни |z| с порогом | G19: =IF(2.667>=2,1,0) -> 1
A20: 17 | B20: 🎓 Универ | C20: OU-процесс, скорость возврата κ=0.5 в минуту. Полупериод возврата (мин)? | E20: =IF(D20="","",IF(ABS(D20-G20)<=ABS(G20)*0.01+0.0001,"✓","✗")) | F20: half-life = ln2 / κ | G20: =LN(2)/0.5 -> 1.3862944
A21: 18 | B21: 🎓 Универ | C21: Лог-остаток обратно в %: x=0.001849 → (e^x − 1)×100 = ? | E21: =IF(D21="","",IF(ABS(D21-G21)<=ABS(G21)*0.01+0.0001,"✓","✗")) | F21: exp(x) − 1, ×100 | G21: =(EXP(0.001849)-1)*100 -> 0.18507105
A22: 19 | B22: 🎓 Универ | C22: Почему σ остатка (0.0003) ≪ σ ноги (~0.01)? Словами. | E22: устно | F22: : Var(a−b−c) при корреляции →1 стремится к 0 | G22: ноги коинтегрированы (ходят вместе) → дисперсии в комбинации (1,−1,−1) почти гасятся
A23: 20 | B23: 💼 Практик | C23: Круг по стакану: продаёшь EUR по EURUSD bid 1.0800 → USD по USDJPY bid 150.00 → выкуп EUR по EURJPY ask 162.40. Сколько EUR на 1 EUR? | E23: =IF(D23="","",IF(ABS(D23-G23)<=ABS(G23)*0.01+0.0001,"✓","✗")) | F23: перемножь исполняемые курсы; выкуп = деление на ask | G23: =1.08*150/162.4 -> 0.99753695
A24: 21 | B24: 💼 Практик | C24: Тот круг — сколько потерял, %? | E24: =IF(D24="","",IF(ABS(D24-G24)<=ABS(G24)*0.01+0.0001,"✓","✗")) | F24: (результат − 1)×100; минус = убыток (издержки съели) | G24: =(1.08*150/162.4-1)*100 -> -0.24630542
A25: 22 | B25: 💼 Практик | C25: Кросс-венью: EURJPY на площадке A = 162.30, на B = 162.10. Базис в пунктах? | E25: =IF(D25="","",IF(ABS(D25-G25)<=ABS(G25)*0.01+0.0001,"✓","✗")) | F25: разница цены ОДНОЙ пары на двух площадках — вот где край живёт | G25: =162.3-162.1 -> 0.2
A26: 23 | B26: 💼 Практик | C26: CIP-форвард EURUSD на год: спот 1.0800, r_USD=5%, r_EUR=3%. Форвард = спот×(1+r_USD)/(1+r_EUR). | E26: =IF(D26="","",IF(ABS(D26-G26)<=ABS(G26)*0.01+0.0001,"✓","✗")) | F26: паритет покрытых процентных ставок | G26: =1.08*(1+0.05)/(1+0.03) -> 1.1009709
A27: 24 | B27: 💼 Практик | C27: Рыночный форвард = 1.0980. Кросс-валютный базис = рынок − CIP-форвард. Посчитай. | E27: =IF(D27="","",IF(ABS(D27-G27)<=ABS(G27)*0.01+0.0001,"✓","✗")) | F27: market − CIP = xccy basis, реальный край банковских десков | G27: =1.098-1.08*(1+0.05)/(1+0.03) -> -0.0029708738
A28: 25 | B28: 💼 Практик | C28: Цикл 4 курсов: EUR→USD 1.08, USD→JPY 150, JPY→GBP 0.0053, GBP→EUR 1.16. Произведение по кругу? | E28: =IF(D28="","",IF(ABS(D28-G28)<=ABS(G28)*0.01+0.0001,"✓","✗")) | F28: произведение по замкнутому циклу; ≠1 = арбитраж (>1 прибыль). Это Bellman–Ford | G28: =1.08*150*0.0053*1.16 -> 0.995976
A29: 26 | B29: 💼 Практик | C29: Годовой Шарп: край 2 б.п./цикл, σ 3 б.п., 50 циклов/день, 252 дня. Sharpe = (2/3)×√(50×252). | E29: =IF(D29="","",IF(ABS(D29-G29)<=ABS(G29)*0.01+0.0001,"✓","✗")) | F29: Sharpe = средн/σ × √(сделок в год). Заоблачный → оттого за край дерётся HFT; в ликвиде он ≈0 после издержек | G29: =(2/3)*SQRT(50*252) -> 74.833148
